MANIFEST.in
README.md
setup.py
payu/__init__.py
payu/client.py
payu/enumerators.py
payu/exceptions.py
payu/payments.py
payu/queries.py
payu/recurring.py
payu/tokenization.py
payu/utils.py
payu_python.egg-info/PKG-INFO
payu_python.egg-info/SOURCES.txt
payu_python.egg-info/dependency_links.txt
payu_python.egg-info/not-zip-safe
payu_python.egg-info/requires.txt
payu_python.egg-info/top_level.txt