Metadata-Version: 1.0
Name: payu-python
Version: 0.1.5
Summary: API wrapper for Payu written in Python
Home-page: https://github.com/GearPlug/payu-python
Author: Miguel Ferrer
Author-email: ingferrermiguel@gmail.com
License: MIT
Platform: UNKNOWN
